[{"Uid":"ade681efbcfc437b8f5126a21b4f1a38","FirstName":"Muskan","LastName":"Soni","Email":[{"Type":"primary","Value":"muskan.soni@loginradius.com"}],"PhoneId":"+2432423423423","Password":"**********","TotalVotes":"0","IsVoted":"true","VotedList":null,"About":"sdffd sdfdsf"},{"Uid":"448db30da06d4f7a8cdc5826a7175e58","FirstName":"Anvi","LastName":"Soni","Email":[{"Type":"primary","Value":"anvisoni@gmail.com"}],"PhoneId":"+323254325435","Password":"**********","TotalVotes":"0","IsVoted":"false","About":"sdffsdf dsfsdff"},{"Uid":"c5bf034aaabc49189a19f70c8eb61450","FirstName":"Sakshi","LastName":"Soni","Email":[{"Type":"primary","Value":"sakshisoni@gmail.com"}],"PhoneId":"+343534534534","Password":"**********","TotalVotes":"0","IsVoted":"false","About":"fdgfdg dgdfgdfg"},{"Uid":"2b3ce432a4b24e0bab4ab5e0e69b885f","FirstName":"Versha","LastName":"Gupta","Email":[{"Type":"primary","Value":"versha@mail7.io"}],"PhoneId":"+345345345345345","Password":"**********","TotalVotes":"2","IsVoted":"false","VotedList":"Muskan , Muskan12","About":"gfhfgh dfhfh"},{"Uid":"9b69f4f584c34eeb8c36409b910c1e2c","FirstName":"Muskan12","LastName":"Soni","Email":[{"Type":"primary","Value":"muskan@mail7.io"}],"PhoneId":"+3453465436","Password":"**********","TotalVotes":"0","IsVoted":"true","VotedList":null,"About":"dsfdsf dfgfdg"}]